azure/mgmt/sqlvirtualmachine/__init__.py
azure/mgmt/sqlvirtualmachine/sql_virtual_machine_management_client.py
azure/mgmt/sqlvirtualmachine/version.py
azure/mgmt/sqlvirtualmachine/models/__init__.py
azure/mgmt/sqlvirtualmachine/models/additional_features_server_configurations.py
azure/mgmt/sqlvirtualmachine/models/additional_features_server_configurations_py3.py
azure/mgmt/sqlvirtualmachine/models/auto_backup_settings.py
azure/mgmt/sqlvirtualmachine/models/auto_backup_settings_py3.py
azure/mgmt/sqlvirtualmachine/models/auto_patching_settings.py
azure/mgmt/sqlvirtualmachine/models/auto_patching_settings_py3.py
azure/mgmt/sqlvirtualmachine/models/availability_group_listener.py
azure/mgmt/sqlvirtualmachine/models/availability_group_listener_paged.py
azure/mgmt/sqlvirtualmachine/models/availability_group_listener_py3.py
azure/mgmt/sqlvirtualmachine/models/key_vault_credential_settings.py
azure/mgmt/sqlvirtualmachine/models/key_vault_credential_settings_py3.py
azure/mgmt/sqlvirtualmachine/models/load_balancer_configuration.py
azure/mgmt/sqlvirtualmachine/models/load_balancer_configuration_py3.py
azure/mgmt/sqlvirtualmachine/models/operation.py
azure/mgmt/sqlvirtualmachine/models/operation_display.py
azure/mgmt/sqlvirtualmachine/models/operation_display_py3.py
azure/mgmt/sqlvirtualmachine/models/operation_paged.py
azure/mgmt/sqlvirtualmachine/models/operation_py3.py
azure/mgmt/sqlvirtualmachine/models/private_ip_address.py
azure/mgmt/sqlvirtualmachine/models/private_ip_address_py3.py
azure/mgmt/sqlvirtualmachine/models/proxy_resource.py
azure/mgmt/sqlvirtualmachine/models/proxy_resource_py3.py
azure/mgmt/sqlvirtualmachine/models/resource.py
azure/mgmt/sqlvirtualmachine/models/resource_identity.py
azure/mgmt/sqlvirtualmachine/models/resource_identity_py3.py
azure/mgmt/sqlvirtualmachine/models/resource_py3.py
azure/mgmt/sqlvirtualmachine/models/server_configurations_management_settings.py
azure/mgmt/sqlvirtualmachine/models/server_configurations_management_settings_py3.py
azure_mgmt_sqlvirtualmachine-0.4.0.dist-info/METADATA
azure_mgmt_sqlvirtualmachine-0.4.0.dist-info/WHEEL
azure_mgmt_sqlvirtualmachine-0.4.0.dist-info/top_level.txt
azure_mgmt_sqlvirtualmachine-0.4.0.dist-info/RECORD
